mf_data/.DS_Store
mf_data/__init__.py
mf_data/econ/__init__.py
mf_data/econ/tgju.py
mf_data/ise/__init__.py
mf_data/ise/codal.py
mf_data/ise/codal_utils/__init__.py
mf_data/ise/codal_utils/clean_and_extend_data.py
mf_data/ise/codal_utils/columns.py
mf_data/ise/codal_utils/constants.py
mf_data/ise/codal_utils/fs_items.py
mf_data/ise/rahavard.py
mf_data/ise/rahavard_utils/__init__.py
mf_data/ise/rahavard_utils/clean_and_extend_data.py
mf_data/ise/rahavard_utils/columns.py
mf_data/ise/rahavard_utils/constants.py
mf_data/ise/tsetmc.py
mf_data/ise/tsetmc_utils/__init__.py
mf_data/ise/tsetmc_utils/clean_and_extend_data.py
mf_data/ise/tsetmc_utils/columns.py
mf_data/ise/tsetmc_utils/constants.py
mf_data/utils/__init__.py
mf_data/utils/async_get.py
mf_data/utils/get.py
metafid_data-0.2.2.dist-info/METADATA
metafid_data-0.2.2.dist-info/WHEEL
metafid_data-0.2.2.dist-info/RECORD
