Metadata-Version: 2.1
Name: metafid-data
Version: 0.2.2
Summary: 
Home-page: https://github.com/yghaderi/metafid-data
Author: Yaghoub Ghadri
Author-email: y.ghaderi@outlook.com
Requires-Python: >=3.10,<4.0
Classifier: Programming Language :: Python :: 3
Classifier: Programming Language :: Python :: 3.10
Classifier: Programming Language :: Python :: 3.11
Requires-Dist: aiohttp (>=3.8.5,<4.0.0)
Requires-Dist: hazm (>=0.9.3,<0.10.0)
Requires-Dist: jdatetime (>=4.1.1,<5.0.0)
Requires-Dist: pandas (>=2.0.0,<3.0.0)
Requires-Dist: requests (>=2.31.0,<3.0.0)
Project-URL: Repository, https://github.com/yghaderi/metafid-data
